makezip.py
makezip-1.0.dist-info/METADATA
makezip-1.0.dist-info/WHEEL
makezip-1.0.dist-info/top_level.txt
makezip-1.0.dist-info/RECORD
